spacedreppy/__init__.py
spacedreppy/memory_models/__init__.py
spacedreppy/memory_models/memory_model.py
spacedreppy/memory_models/sm2.py
spacedreppy/schedulers/__init__.py
spacedreppy/schedulers/sm2.py
spacedreppy/schedulers/spaced_repetition_scheduler.py
spacedreppy-0.1.2.dist-info/LICENSE
spacedreppy-0.1.2.dist-info/WHEEL
spacedreppy-0.1.2.dist-info/METADATA
spacedreppy-0.1.2.dist-info/RECORD
