Metadata-Version: 2.1
Name: spacedreppy
Version: 0.1.2
Summary: A spaced repetition Python library.
License: MIT
Keywords: Spaced-repetition
Author: Louis Schlessinger
Author-email: 2996982+lschlessinger1@users.noreply.github.com
Requires-Python: >=3.9,<4.0
Classifier: License :: OSI Approved :: MIT License
Classifier: Programming Language :: Python :: 3
Classifier: Programming Language :: Python :: 3.10
Classifier: Programming Language :: Python :: 3.9
